aiconclave/__init__.py
aiconclave/constants.py
aiconclave/main.py
aiconclave/streamlit_app.py
aiconclave/test.py
aiconclave/assets/config.json
aiconclave/assets/chrome_dino/jump.mp3
aiconclave/assets/tekken/TekkenGame.exe
aiconclave/games/__init__.py
aiconclave/games/air_drums.py
aiconclave/games/chrome_dino.py
aiconclave/games/motor_rider.py
aiconclave/games/pin_ball.py
aiconclave/games/road_rash-punch-test.py
aiconclave/games/road_rash.py
aiconclave/games/tekken.py
aiconclave/games/tekken_players.py
aiconclave/trackers/HandTrackingModule.py
aiconclave/trackers/PoseModule.py
aiconclave/trackers/__init__.py
aiconclave-0.1.3.dist-info/METADATA
aiconclave-0.1.3.dist-info/WHEEL
aiconclave-0.1.3.dist-info/entry_points.txt
aiconclave-0.1.3.dist-info/top_level.txt
aiconclave-0.1.3.dist-info/RECORD
